igorskis_framework/__init__.py
igorskis_framework/base_model.py
igorskis_framework/cli.py
igorskis_framework/cli_functions.py
igorskis_framework/config.py
igorskis_framework/help_functions.py
igorskis_framework/models.py
igorskis_framework/restart_handler.py
igorskis_framework/router.py
igorskis_framework/templates.py
igorskis_framework/validator.py
igorskis_framework-1.0.2.dist-info/licenses/LICENSE
igorskis_framework-1.0.2.dist-info/METADATA
igorskis_framework-1.0.2.dist-info/WHEEL
igorskis_framework-1.0.2.dist-info/entry_points.txt
igorskis_framework-1.0.2.dist-info/top_level.txt
igorskis_framework-1.0.2.dist-info/RECORD
