Metadata-Version: 2.4
Name: igorskis-framework
Version: 1.0.2
Summary: Igorskis Framework. A web framework for creating web applications.
Author: igorskis
Author-email: usikowigor@gmail.com
License: MIT
Classifier: License :: OSI Approved :: MIT License
Classifier: Programming Language :: Python :: 3
License-File: LICENSE
Requires-Dist: jinja2
Requires-Dist: watchdog
Requires-Dist: gunicorn
Dynamic: author
Dynamic: author-email
Dynamic: classifier
Dynamic: description
Dynamic: description-content-type
Dynamic: license
Dynamic: license-file
Dynamic: requires-dist
Dynamic: summary
